setup.py
gagorastertiler/__init__.py
gagorastertiler/raster2tiles.py
gagorastertiler/test.py
gagorastertiler.egg-info/PKG-INFO
gagorastertiler.egg-info/SOURCES.txt
gagorastertiler.egg-info/dependency_links.txt
gagorastertiler.egg-info/requires.txt
gagorastertiler.egg-info/top_level.txt