Metadata-Version: 1.0
Name: gagorastertiler
Version: 0.0.1
Summary: An raster tiler tool
Home-page: UNKNOWN
Author: dutengteng
Author-email: dutengteng1@163.com
License: MIT Licence
Keywords: pip,gagorastertiler,rastertile
Platform: any
